webcode_tk/__init__.py
webcode_tk/animation_tools.py
webcode_tk/cascade_tools.py
webcode_tk/color_keywords.py
webcode_tk/color_tools.py
webcode_tk/contrast_tools.py
webcode_tk/css_tools.py
webcode_tk/font_tools.py
webcode_tk/html_tools.py
webcode_tk/sample_report.json
webcode_tk/utils.py
webcode_tk/ux_tools.py
webcode_tk/validator_tools.py
webcode_tk-1.2.11.dist-info/METADATA
webcode_tk-1.2.11.dist-info/WHEEL
webcode_tk-1.2.11.dist-info/licenses/LICENSE.rst
webcode_tk-1.2.11.dist-info/RECORD
